{
  "static": true,
  "className": "MagickNET",
  "delegates": [
    {
      "name": "Log",
      "arguments": [
        {
          "name": "type",
          "type": "LogEvents"
        },
        {
          "name": "value",
          "type": "IntPtr"
        }
      ]
    }
  ],
  "properties": [
    {
      "name": "Delegates",
      "type": "string",
      "readonly": true
    },
    {
      "name": "Features",
      "type": "string",
      "readonly": true
    }
  ],
  "methods": [
    {
      "name": "GetFonts",
      "type": "Instance",
      "throws": true,
      "cleanup": {
        "name": "DisposeFonts"
      },
      "arguments": [
        {
          "name": "length",
          "type": "size_t",
          "out": true
        }
      ]
    },
    {
      "name": "GetFontName",
      "type": "string",
      "arguments": [
        {
          "name": "instance",
          "type": "Instance"
        },
        {
          "name": "index",
          "type": "size_t"
        }
      ]
    },
    {
      "name": "GetFontFamily",
      "type": "string",
      "arguments": [
        {
          "name": "instance",
          "type": "Instance"
        },
        {
          "name": "index",
          "type": "size_t"
        }
      ]
    },
    {
      "name": "DisposeFonts",
      "arguments": [
        {
          "name": "instance",
          "type": "Instance"
        }
      ]
    },
    {
      "name": "SetLogDelegate",
      "arguments": [
        {
          "name": "method",
          "type": "LogDelegate"
        }
      ]
    },
    {
      "name": "SetLogEvents",
      "arguments": [
        {
          "name": "events",
          "type": "string"
        }
      ]
    },
    {
      "name": "SetRandomSeed",
      "arguments": [
        {
          "name": "value",
          "type": "long"
        }
      ]
    }
  ]
}
